[
    {
        "name": "BossDeathRein",
        "trigger": "turn_change",
        "level_nid": "4",
        "condition": "True",
        "commands": [],
        "only_once": false,
        "priority": 19,
        "_source": [
            "if;{v:AckerRein} == 1",
            "    move_cursor;21, 15",
            "    wait;500",
            "    spawn_group;AckerRein;south;AckerRein;normal;push",
            "    wait;500",
            "    inc_level_var;AckerRein;1",
            "end",
            "",
            "if;{v:BrassRein} == 1",
            "    move_cursor;0, 15",
            "    wait;500",
            "    spawn_group;BrassRein;south;BrassRein;normal;push",
            "    wait;500",
            "    inc_level_var;BrassRein;1",
            "end",
            "",
            "if;{v:EmberRein} == 1",
            "    move_cursor;0, 0",
            "    wait;500",
            "    spawn_group;EmberRein;west;EmberRein;normal;push",
            "    wait;500",
            "    inc_level_var;EmberRein;1",
            "end",
            "",
            "if;{v:DavenRein} == 1",
            "    move_cursor;21, 0",
            "    wait;500",
            "    spawn_group;DavenRein;north;DavenRein;normal;push",
            "    wait;500",
            "    inc_level_var;DavenRein;1",
            "end",
            "",
            "if;{v:CawthRein} == 1",
            "    move_cursor;0, 11",
            "    wait;500",
            "    spawn_group;CawthRein;west;CawthRein;normal;push",
            "    wait;500",
            "    inc_game_var;CawthRein;1",
            "end"
        ]
    }
]