[
    {
        "name": "HouseShayla",
        "trigger": null,
        "level_nid": null,
        "condition": "True",
        "commands": [],
        "only_once": true,
        "priority": 20,
        "_source": [
            "transition;Close",
            "change_background;House",
            "transition;Open",
            "add_portrait;Shayla;OffscreenRight",
            "bop_portrait;Shayla",
            "speak;Shayla;Mom!",
            "move_portrait;Shayla;Right",
            "bop_portrait;Shayla",
            "speak;Shayla;Sis!",
            "move_portrait;Shayla;MidRight",
            "expression;Shayla;HalfCloseEyes",
            "s;Shayla;Maybe they left a note, or...{w} wait.{w} This is...{w} my training lance?{w}{clear}...{w}{c:expression;Shayla;CloseEyes} Crap, I remember now...{w} Was that really just earlier today...?",
            "music;But A Memory",
            "end_skip",
            "transition;Close;1000;255,255,255",
            "remove_portrait;Shayla",
            "",
            "",
            "# Flashback",
            "change_background;House1Sepia",
            "multi_add_portrait;ShaylaMother;Left;ShaylaSister;OffscreenRight",
            "transition;open;1000;255,255,255",
            "wait;250",
            "move_portrait;ShaylaSister;Right",
            "add_portrait;SShayla;OffscreenRight",
            "s;ShaylaSister;Mo-om!{w} Shayla did it again!",
            "wait;250",
            "move_portrait;ShaylaSister;MidLeft",
            "move_portrait;SShayla;FarRight",
            "s;SShayla;Shut UP, sis!{w} Give me that back!",
            "move_portrait;ShaylaSister;OffscreenLeft",
            "remove_portrait;ShaylaSister",
            "move_portrait;SShayla;OffscreenLeft",
            "mirror_portrait;SShayla",
            "#Sister runs from off-screen left to off-screen right. Shayla follows",
            "s;ShaylaMother;This again?{w} What is it now, you two?",
            "add_portrait;ShaylaSister;OffscreenLeft",
            "move_portrait;ShaylaSister;MidRight",
            "add_portrait;SShayla;OffscreenLeft",
            "move_portrait;SShayla;MidLeft",
            "mirror_portrait;SShayla",
            "s;SShayla;Nothing!",
            "mirror_portrait;SShayla",
            "s;SShayla;Stop running, you little-!",
            "move_portrait;ShaylaSister;Right",
            "#\t//They run across again. Then, as Sister runs across a third time, Shayla intercepts her on the right side of the screen",
            "move_portrait;SShayla;FarRight",
            "mirror_portrait;SShayla",
            "wait;250",
            "s;ShaylaSister;Let me go!",
            "bop_portrait;SShayla",
            "s;SShayla;Gimme that!{w} Hah!",
            "mirror_portrait;ShaylaSister",
            "move_portrait;ShaylaSister;MidRight",
            "s;ShaylaMother;Shayla.{w} What was it this time?",
            "s;SShayla;N-nothing!{w} It doesn't matter!",
            "s;ShaylaSister;She's lying again, mom!",
            "s;ShaylaMother;Show it to me.{w} Now.",
            "s;SShayla;...{w} Fine! Take it, for all I care.|It was a piece of junk, anyway.",
            "s;ShaylaMother;Seriously?{w} Another broken lance!?|These things don't grow on trees, you know!|I paid good coin for this!",
            "s;SShayla;Then you got ripped off.",
            "s;ShaylaMother;Shayla!",
            "s;SShayla;What!?{w} What do you want me to say!?{w}{clear}I'm sorry I broke your crappy lance just like all the other crappy lances.",
            "s;ShaylaMother;Damn it, Shay!{w} It's always the same thing with you!{w}{clear}Never thinking before you act, always running your mouth!|If your father could see you-!",
            "s;SShayla;Stop it!{w} He has nothing to do with this!",
            "s;ShaylaMother;If he were still around, maybe he would've taught you some discipline.{w}{clear}At this rate, you'll never even be half the warrior he was...",
            "s;SShayla;J-just...{w} just shut up!! Shut up about Dad, and shut up about your stupid discipline!|You have no idea how disciplined I really am!{w} I only broke the lance because I was trying so hard!",
            "s;ShaylaMother;You only broke it because you weren't trying hard enough!",
            "s;SShayla;Y-you-!{w} I...|I-I hate you!{w} I hate both of you!|Take your stupid lance and choke on it!",
            "#//Shayla runs off",
            "mirror_portrait;SShayla",
            "wait;250",
            "move_portrait;SShayla;OffscreenRight",
            "wait;250",
            "s;ShaylaMother;Shayla!{w} Come back here!{w} Shayla!!",
            "",
            "",
            "transition;close;500;255,255,255",
            "multi_remove_portrait;ShaylaSister;SShayla;ShaylaMother",
            "change_background;House",
            "add_portrait;Shayla;MidRight",
            "expression;Shayla;CloseEyes",
            "end_skip",
            "transition;open;500;255,255,255",
            "",
            "s;Shayla;I really said all that...{c:expression;Shayla;HalfCloseEyes}{w} over a stupid lance?{w}{clear}Who the hell cares?{w} Jeez...",
            "expression;Shayla;CloseEyes",
            "mirror_portrait;Shayla",
            "s;Shayla;I...{w} I hope they're...{w}{clear}I-I mean, if those were the last words I ever got to...",
            "move_portrait;Shayla;FarRight",
            "bop_portrait;Shayla",
            "expression;Shayla;OpenEyes",
            "s;Shayla;Nah, I'm not even gonna think about that.{w} Just gonna have to go find them.{w}{clear}Hmmm...{w} {c:expression;Shayla;Smile}you know, even broken, this hunk of junk could have a real nasty swing...|'s gotta be better than leaving here empty-handed.",
            "",
            "",
            "transition;close",
            "remove_portrait;Shayla",
            "change_background",
            "music_fade_back",
            "transition;Open",
            "",
            "end_skip",
            "give_item;Shayla;Heartache",
            "",
            "if;game.mode.nid != 'Normal'",
            "    remove_item_component;Shayla;Heartache;uses",
            "    add_item_component;Shayla;Heartache;uses;8",
            "end",
            "",
            "if;'{v:PlayerReverse}' == 'Reversal'",
            "    add_item_component;Shayla;Heartache;weapon_type;'Sword'",
            "    add_item_component;Shayla;Heartache;map_cast_anim;'Map_Sword_Cast'",
            "elif;'{v:PlayerReverse}' == 'Double'",
            "    add_item_component;Shayla;Heartache;weapon_type;'Lance'",
            "    add_item_component;Shayla;Heartache;map_cast_anim;'Map_Lance_Cast'",
            "else",
            "    add_item_component;Shayla;Heartache;weapon_type;'Axe'",
            "    add_item_component;Shayla;Heartache;map_cast_anim;'Map_Axe_Cast'",
            "end",
            "",
            "if;'{v:ReverseRecruitment}' == 'No'",
            "    inc_game_var;ShaylaVisited;1",
            "end",
            "",
            "",
            "give_exp;Shayla;40",
            "",
            "if;not has_achievement('1')",
            "    update_achievement;1;No Last Word;Viewed Shayla's Flashback in Ch1.",
            "    complete_achievement;1;1;banner",
            "end",
            ""
        ]
    }
]